[{"id":1,"name":"Toyota","country":"Japan","founded_year":1937},{"id":2,"name":"Ford","country":"USA","founded_year":1903},{"id":3,"name":"Volkswagen","country":"Germany","founded_year":1937},{"id":4,"name":"Honda","country":"Japan","founded_year":1948},{"id":5,"name":"BMW","country":"Germany","founded_year":1916},{"id":6,"name":"Mercedes-Benz","country":"Germany","founded_year":1926},{"id":7,"name":"Hyundai","country":"South Korea","founded_year":1967},{"id":8,"name":"Nissan","country":"Japan","founded_year":1933},{"id":9,"name":"Chevrolet","country":"USA","founded_year":1911},{"id":10,"name":"Kia","country":"South Korea","founded_year":1944}]